lingcorpora/__init__.py
lingcorpora/corpus.py
lingcorpora/exceptions.py
lingcorpora/functions.py
lingcorpora/params_container.py
lingcorpora/result.py
lingcorpora/target.py
lingcorpora/corpora/__init__.py
lingcorpora/corpora/ady_corpus.py
lingcorpora/corpora/alb_corpus.py
lingcorpora/corpora/arkhangelskiy_corpora.py
lingcorpora/corpora/arm_corpus.py
lingcorpora/corpora/bam_corpus.py
lingcorpora/corpora/bua_corpus.py
lingcorpora/corpora/dan_corpus.py
lingcorpora/corpora/deu_corpus.py
lingcorpora/corpora/emk_corpus.py
lingcorpora/corpora/est_corpus.py
lingcorpora/corpora/grk_corpus.py
lingcorpora/corpora/hin_corpus.py
lingcorpora/corpora/kal_corpus.py
lingcorpora/corpora/kat_corpus.py
lingcorpora/corpora/kaz_corpus.py
lingcorpora/corpora/mon_corpus.py
lingcorpora/corpora/rus_corpus.py
lingcorpora/corpora/rus_parallel_corpus.py
lingcorpora/corpora/rus_pol_corpus.py
lingcorpora/corpora/tat_corpus.py
lingcorpora/corpora/udm_corpus.py
lingcorpora/corpora/yid_corpus.py
lingcorpora/corpora/zho_corpus.py
lingcorpora/corpora/zho_eng_corpus.py
lingcorpora-2.0.dist-info/LICENSE.md
lingcorpora-2.0.dist-info/METADATA
lingcorpora-2.0.dist-info/WHEEL
lingcorpora-2.0.dist-info/top_level.txt
lingcorpora-2.0.dist-info/RECORD
