Metadata-Version: 2.1
Name: lingcorpora
Version: 2.0
Summary: API for text corpora
Home-page: https://github.com/lingcorpora/lingcorpora.py
Author: Alexey Koshevoy, Anna Klezovich, Anna Zueva, Artem Kopetsky, Diana Malyshok, Ekaterina Gerasimenko, George Moroz, Maria Terekhina, Mark Sobolev, Michael Voronov, Ustinya Kosheleva
Author-email: katgerasimenko@gmail.com
License: MIT
Keywords: corpora,api,language
Platform: UNKNOWN
Requires-Python: >=3.5
